CHANGELOG.md
LICENSE
rest_live/__init__.py
rest_live/apps.py
rest_live/consumers.py
rest_live/mixins.py
rest_live/routers.py
rest_live/signals.py
rest_live/testing.py
django_rest_live-0.7.0.dist-info/LICENSE
django_rest_live-0.7.0.dist-info/WHEEL
django_rest_live-0.7.0.dist-info/METADATA
django_rest_live-0.7.0.dist-info/RECORD
