Metadata-Version: 2.1
Name: django-rest-live
Version: 0.7.0
Summary: Subscriptions for Django REST Framework over Websockets.
Home-page: https://github.com/pennlabs/django-rest-live
License: MIT
Author: Penn Labs
Author-email: contact@pennlabs.org
Requires-Python: >=3.7
Classifier: Framework :: Django
Classifier: License :: OSI Approved :: MIT License
Classifier: Programming Language :: Python :: 3
Classifier: Programming Language :: Python :: 3.10
Classifier: Programming Language :: Python :: 3.7
Classifier: Programming Language :: Python :: 3.8
Classifier: Programming Language :: Python :: 3.9
Requires-Dist: Django (>=3.1)
Requires-Dist: channels (>=2.0.0)
Requires-Dist: djangorestframework (>=3.11)
Project-URL: Documentation, https://django-rest-live.readthedocs.io/en/latest/
Project-URL: Repository, https://github.com/pennlabs/django-rest-live
